vclones
