Metadata-Version: 1.1
Name: vmware-clones
Version: 0.2.11
Summary: Clone running vmware virtual machines running on preconfigured cluster
Home-page: https://github.com/gmelillo/esxi-backup
Author: Gabriel Melillo
Author-email: gabriel@melillo.me
License: GNU GENERAL PUBLIC LICENSE
Platform: OS Independent
Classifier: Development Status :: 2 - Pre-Alpha
Classifier: Intended Audience :: Information Technology
Classifier: Operating System :: OS Independent
Classifier: Programming Language :: Python
Classifier: Programming Language :: Python :: 2.6
Classifier: Programming Language :: Python :: 2.7
